termux_api_python/__init__.py
termux_api_python/termux_api.py
termux_api_python-0.1.1.dist-info/METADATA
termux_api_python-0.1.1.dist-info/WHEEL
termux_api_python-0.1.1.dist-info/top_level.txt
termux_api_python-0.1.1.dist-info/RECORD
