Metadata-Version: 2.1
Name: termux-api-python
Version: 0.1.1
Summary: A Python wrapper for the Termux API commands
Home-page: https://github.com/Kamanati/termux-api-python
Author: hasanfq6
Author-email: hasanfq818@gmail.com
Keywords: termux,android,api,wrapper
Classifier: Programming Language :: Python :: 3
Classifier: License :: OSI Approved :: MIT License
Classifier: Operating System :: Android
Classifier: Topic :: Software Development :: Libraries :: Python Modules
Classifier: Intended Audience :: Developers
Requires-Python: >=3.6
